discoverpagination/__init__.py
discoverpagination/fuzzyfind.py
discoverpagination/helpers.py
discoverpagination/paginateddocument.py
test/__init__.py
test/test_helpers.py
test/test_paginateddocument.py
DiscoverPagination-0.1.4.dist-info/LICENSE
DiscoverPagination-0.1.4.dist-info/METADATA
DiscoverPagination-0.1.4.dist-info/WHEEL
DiscoverPagination-0.1.4.dist-info/top_level.txt
DiscoverPagination-0.1.4.dist-info/RECORD
