Metadata-Version: 2.1
Name: DiscoverPagination
Version: 0.1.4
Summary: UNKNOWN
Home-page: UNKNOWN
Author-email: dhking@wharton.upenn.edu
License: MIT
Platform: UNKNOWN
Requires-Dist: fuzzywuzzy
Requires-Dist: python-Levenshtein
